sokoweb/__init__.py
sokoweb/docker/Dockerfile
sokoweb/docker/docker-compose.yml
sokoweb/sokoweb/__init__.py
sokoweb/sokoweb/api.py
sokoweb/sokoweb/auth.py
sokoweb/sokoweb/cli.py
sokoweb/sokoweb/create_tables.py
sokoweb/sokoweb/credit_manager.py
sokoweb/sokoweb/crypto.py
sokoweb/sokoweb/database.py
sokoweb/sokoweb/db_models.py
sokoweb/sokoweb/debug.py
sokoweb/sokoweb/kbucket.py
sokoweb/sokoweb/marketplace.py
sokoweb/sokoweb/messages.py
sokoweb/sokoweb/models.py
sokoweb/sokoweb/mpesa.py
sokoweb/sokoweb/node.py
sokoweb/sokoweb/product.py
sokoweb/sokoweb/proof_of_bandwidth.py
sokoweb/sokoweb/remote_node.py
sokoweb/sokoweb/routing_table.py
sokoweb/sokoweb/storage_messages.py
sokoweb/sokoweb/storage_node.py
sokoweb/sokoweb/storage_service.py
sokoweb/sokoweb/utils.py
sokoweb/sokoweb/validators.py
sokoweb/sokoweb/wait_for_postgres.py
sokoweb-0.1.50.dist-info/METADATA
sokoweb-0.1.50.dist-info/WHEEL
sokoweb-0.1.50.dist-info/entry_points.txt
sokoweb-0.1.50.dist-info/top_level.txt
sokoweb-0.1.50.dist-info/RECORD
